epyqlib/__init__.py
epyqlib/_build.py
epyqlib/_version.py
epyqlib/abstractcolumns.py
epyqlib/abstractpluginclass.py
epyqlib/attrsmodel.py
epyqlib/authorization.py
epyqlib/autodevice/__init__.py
epyqlib/autodevice/build.py
epyqlib/autodevice/cli.py
epyqlib/autodevice/template/auto_parameters.epc
epyqlib/autodevice/template/auto_parameters.epp
epyqlib/autodevice/template/auto_parameters.py
epyqlib/autodevice/template/auto_parameters.ui
epyqlib/busproxy.py
epyqlib/cangenmanual.py
epyqlib/canneo.py
epyqlib/checkresultmodel.py
epyqlib/chunkedmemorycache.py
epyqlib/cli/__init__.py
epyqlib/cli/audit.py
epyqlib/cli/generateversion.py
epyqlib/cli/main.py
epyqlib/cli/phabricator_extract.py
epyqlib/cli/versionfile.py
epyqlib/cmemoryparser.py
epyqlib/collectdevices.py
epyqlib/compileui.py
epyqlib/compoundscale.py
epyqlib/compoundscale.ui
epyqlib/compoundscaleleft.py
epyqlib/compoundscaleleft.ui
epyqlib/compoundscaleleftplugin.py
epyqlib/compoundscaleplugin.py
epyqlib/compoundtoggle.py
epyqlib/compoundtoggle.ui
epyqlib/compoundtoggleplugin.py
epyqlib/csvwindow.py
epyqlib/datalogger.py
epyqlib/delegates.py
epyqlib/device.py
epyqlib/device.ui
epyqlib/deviceextension.py
epyqlib/devicetree.py
epyqlib/devicetreeview.py
epyqlib/devicetreeview.ui
epyqlib/devicetreeviewplugin.py
epyqlib/dualscale.py
epyqlib/dualscale.ui
epyqlib/dualscaleplugin.py
epyqlib/faultlogmodel.py
epyqlib/faultlogview.py
epyqlib/faultlogview.ui
epyqlib/flash.py
epyqlib/fontawesome.ofl_license.txt
epyqlib/form.py
epyqlib/formplugin.py
epyqlib/genbuildinfo.py
epyqlib/generaterevision.py
epyqlib/hildevice.py
epyqlib/hmidialog.py
epyqlib/hmidialog.ui
epyqlib/icon.ico
epyqlib/icon.png
epyqlib/iogroup.py
epyqlib/iogroup.ui
epyqlib/iogroupplugin.py
epyqlib/iopoint.py
epyqlib/iopoint.ui
epyqlib/iopointplugin.py
epyqlib/listmenu.py
epyqlib/listmenuview.py
epyqlib/listmenuview.ui
epyqlib/listmenuviewplugin.py
epyqlib/listselect.py
epyqlib/listselect.ui
epyqlib/listselectplugin.py
epyqlib/mixins.py
epyqlib/numberpad.py
epyqlib-2022.2.1.dist-info/entry_points.txt
epyqlib-2022.2.1.dist-info/COPYING
epyqlib-2022.2.1.dist-info/WHEEL
epyqlib-2022.2.1.dist-info/METADATA
epyqlib-2022.2.1.dist-info/RECORD
