Metadata-Version: 2.1
Name: epyqlib
Version: 2022.2.1
Summary: 
Author: Alex Anker
Author-email: alex.anker@epcpower.com
Requires-Python: >=3.7,<4.0
Classifier: Programming Language :: Python :: 3
Classifier: Programming Language :: Python :: 3.10
Classifier: Programming Language :: Python :: 3.7
Classifier: Programming Language :: Python :: 3.8
Classifier: Programming Language :: Python :: 3.9
Requires-Dist: GitPython (==2.1.15)
Requires-Dist: Pint (==0.11)
Requires-Dist: PyQt5 (>=5.13.0)
Requires-Dist: PyQt5Designer (>=5.14.1,<6.0.0)
Requires-Dist: QtAwesome (==0.6.0)
Requires-Dist: Twisted (==21.2.0)
Requires-Dist: alqtendpy (==0.0.4)
Requires-Dist: appdirs (==1.4.3)
Requires-Dist: arrow (==0.12.1)
Requires-Dist: attrs (>=19.3.0)
Requires-Dist: bitstruct (==6.0.0)
Requires-Dist: boto3 (==1.14.41.0)
Requires-Dist: boto3-type-annotations (==0.3.1)
Requires-Dist: canmatrix (==0.9.1)
Requires-Dist: certifi (==2020.6.20)
Requires-Dist: certitude (==1.0.1); sys_platform == "Darwin"
Requires-Dist: click (<=7.1.2)
Requires-Dist: dulwich (==0.20.6)
Requires-Dist: fab (==3.0.0)
Requires-Dist: graham (==0.1.11)
Requires-Dist: marshmallow (==2.16.3)
Requires-Dist: natsort (==5.5.0)
Requires-Dist: paho-mqtt (==1.4.0)
Requires-Dist: pyelftools (==0.26)
Requires-Dist: pysunspec (>=2.1.1,<3.0.0)
Requires-Dist: pytest (==5.3.5)
Requires-Dist: pytest-qt (==3.3.0)
Requires-Dist: pytest-rerunfailures (==5.0)
Requires-Dist: pytest-twisted (<=1.13.4)
Requires-Dist: pytest-xvfb (==1.2.0)
Requires-Dist: python-can (>=3.3.4,<4.0.0)
Requires-Dist: python-dateutil (==2.7.5)
Requires-Dist: python-docx (==0.8.7)
Requires-Dist: python-dotenv (==0.9.1)
Requires-Dist: qt5reactor (==0.5)
Requires-Dist: siphash-cffi (>=0.1.4,<0.2.0)
Requires-Dist: sunspecdemo (>=0.1.6,<0.2.0)
Requires-Dist: treq (==21.1.0)
Requires-Dist: twine (==1.13.0)
